yellowbox_heksher/__init__.py
yellowbox_heksher/_version.py
yellowbox_heksher/heksher_service.py
yellowbox_heksher-0.2.1.dist-info/LICENSE
yellowbox_heksher-0.2.1.dist-info/WHEEL
yellowbox_heksher-0.2.1.dist-info/METADATA
yellowbox_heksher-0.2.1.dist-info/RECORD
