Metadata-Version: 2.1
Name: yellowbox-heksher
Version: 0.2.1
Summary: 
License: MIT
Author: Biocatch LTD
Author-email: serverteam@biocatch.com
Requires-Python: >=3.7,<4.0
Classifier: License :: OSI Approved :: MIT License
Classifier: Programming Language :: Python :: 3
Classifier: Programming Language :: Python :: 3.10
Classifier: Programming Language :: Python :: 3.7
Classifier: Programming Language :: Python :: 3.8
Classifier: Programming Language :: Python :: 3.9
Requires-Dist: httpx
Requires-Dist: yellowbox[postgresql] (>=0.6.4)
